eye_cli/__init__.py
eye_cli/__main__.py
eye_cli/data/__init__.py
eye_cli/data/data.py
eye_cli/dl.py
eye_cli/hmm.py
eye_cli/move/__init__.py
eye_cli/move/export.py
eye_cli/rc.py
eye_cli/util.py
eye_cli/vms.py
eye_cli-0.29.0.dist-info/METADATA
eye_cli-0.29.0.dist-info/WHEEL
eye_cli-0.29.0.dist-info/entry_points.txt
eye_cli-0.29.0.dist-info/RECORD
