Metadata-Version: 2.1
Name: eye-cli
Version: 0.29.0
Summary: CLI for Kestrels
Author: Will Barley
Author-email: will.barley@geckorobotics.com
Requires-Python: >=3.12,<4.0
Classifier: Programming Language :: Python :: 3
Classifier: Programming Language :: Python :: 3.12
Requires-Dist: click (>=8.1.7,<8.2.0)
Requires-Dist: inquirer (>=3.4.0,<4.0.0)
Requires-Dist: pyperclip (>=1.9.0,<2.0.0)
Requires-Dist: typer (>=0.12.5,<0.13.0)
Requires-Dist: yaspin (>=3.0.2,<4.0.0)
